AliYunyunXiaoZhuliQiye10BeiXiaonengTishengAnliJi/README.md
AliYunyunXiaoZhuliQiye10BeiXiaonengTishengAnliJi/__init__.py
AliYunyunXiaoZhuliQiye10BeiXiaonengTishengAnliJi/__main__.py
AliYunyunXiaoZhuliQiye10BeiXiaonengTishengAnliJi/file.pdf
AliYunyunXiaoZhuliQiye10BeiXiaonengTishengAnliJi/index.html
ali_yunyun_xiao_zhuli_qiye_10_bei_xiaoneng_tisheng_anli_ji-2024.3.6.0.dist-info/METADATA
ali_yunyun_xiao_zhuli_qiye_10_bei_xiaoneng_tisheng_anli_ji-2024.3.6.0.dist-info/WHEEL
ali_yunyun_xiao_zhuli_qiye_10_bei_xiaoneng_tisheng_anli_ji-2024.3.6.0.dist-info/entry_points.txt
ali_yunyun_xiao_zhuli_qiye_10_bei_xiaoneng_tisheng_anli_ji-2024.3.6.0.dist-info/top_level.txt
ali_yunyun_xiao_zhuli_qiye_10_bei_xiaoneng_tisheng_anli_ji-2024.3.6.0.dist-info/RECORD
